desktop/__init__.py
desktop/dialog.py
desktop/windows.py
desktop3-0.5.4.dist-info/METADATA
desktop3-0.5.4.dist-info/WHEEL
desktop3-0.5.4.dist-info/top_level.txt
desktop3-0.5.4.dist-info/zip-safe
desktop3-0.5.4.dist-info/RECORD
