Metadata-Version: 2.4
Name: desktop3
Version: 0.5.4
Summary: Simple desktop integration for Python.
Home-page: https://github.com/eight04/pyDesktop3
Author: Paul Boddie
Author-email: paul@boddie.org.uk
Maintainer: eight04
Maintainer-email: eight04@gmail.com
License: LGPLv3+
Keywords: desktop, startfile, DESKTOP_LAUNCH, KDE, KDE4, GNOME, XFCE, XFCE4, Lubuntu,dialog, kdialog, zenity, Xdialog, X11, start, open, opener, launch,launcher
Platform: any
Classifier: Development Status :: 5 - Production/Stable
Classifier: Intended Audience :: Developers
Classifier: License :: OSI Approved :: GNU Lesser General Public License v3 or later (LGPLv3+)
Classifier: Natural Language :: Chinese (Traditional)
Classifier: Environment :: MacOS X
Classifier: Environment :: Other Environment
Classifier: Environment :: Win32 (MS Windows)
Classifier: Environment :: X11 Applications
Classifier: Environment :: X11 Applications :: Gnome
Classifier: Environment :: X11 Applications :: KDE
Classifier: Operating System :: OS Independent
Classifier: Programming Language :: Python :: 3
Classifier: Programming Language :: Python :: 3.5
Classifier: Topic :: Desktop Environment :: Window Managers :: XFCE
Classifier: Topic :: Utilities
